github2pypi/__init__.py
github2pypi/generate_pypi_readme.py
github2pypi/publish_to_pypi.py
github2pypi/replace_url.py
github2pypi/run_tests.py
octomap/__init__.py
octomap/dynamicEDT3D_defs.pxd
octomap/include_and_setting.h
octomap/octomap.cpp
octomap/octomap.cpython-39-x86_64-linux-gnu.so
octomap/octomap.pyx
octomap/octomap_defs.pxd
octomap/lib/libdynamicedt3d.a
octomap/lib/libdynamicedt3d.so
octomap/lib/libdynamicedt3d.so.1.10
octomap/lib/libdynamicedt3d.so.1.10.0
octomap/lib/liboctomap.a
octomap/lib/liboctomap.so
octomap/lib/liboctomap.so.1.10
octomap/lib/liboctomap.so.1.10.0
octomap/lib/liboctomath.a
octomap/lib/liboctomath.so
octomap/lib/liboctomath.so.1.10
octomap/lib/liboctomath.so.1.10.0
octomap2python-0.2.0.data/data/octomap/lib/libdynamicedt3d.a
octomap2python-0.2.0.data/data/octomap/lib/libdynamicedt3d.so
octomap2python-0.2.0.data/data/octomap/lib/liboctomap.a
octomap2python-0.2.0.data/data/octomap/lib/liboctomap.so
octomap2python-0.2.0.data/data/octomap/lib/liboctomath.a
octomap2python-0.2.0.data/data/octomap/lib/liboctomath.so
octomap2python.libs/liboctomath-763695d4.so.1.10.0
octomap2python-0.2.0.dist-info/METADATA
octomap2python-0.2.0.dist-info/WHEEL
octomap2python-0.2.0.dist-info/entry_points.txt
octomap2python-0.2.0.dist-info/top_level.txt
octomap2python-0.2.0.dist-info/RECORD
octomap2python-0.2.0.dist-info/licenses/LICENSE
