Metadata-Version: 2.4
Name: octomap2python
Version: 0.2.0
Summary: Python binding of the OctoMap library with bundled shared libraries.
Author-email: Spinkoo <lespinkoo@gmail.com>
License: MIT License
Project-URL: Homepage, https://github.com/Spinkoo/octomap2python
Project-URL: Repository, https://github.com/Spinkoo/octomap2python
Project-URL: Documentation, https://github.com/Spinkoo/octomap2python#readme
Project-URL: Bug Tracker, https://github.com/Spinkoo/octomap2python/issues
Keywords: octomap,occupancy,mapping,robotics,3d,bundled-libs,python
Classifier: Development Status :: 5 - Production/Stable
Classifier: Intended Audience :: Developers
Classifier: Intended Audience :: Science/Research
Classifier: Natural Language :: English
Classifier: Programming Language :: Python :: 3
Classifier: Programming Language :: Python :: 3.9
Classifier: Programming Language :: Python :: 3.10
Classifier: Programming Language :: Python :: 3.11
Classifier: Programming Language :: Python :: 3.12
Classifier: Programming Language :: Python :: Implementation :: CPython
Classifier: Topic :: Scientific/Engineering
Classifier: Topic :: Software Development :: Libraries :: Python Modules
Requires-Python: >=3.9
License-File: LICENSE
Requires-Dist: numpy>=1.16.0
Provides-Extra: visualization
Requires-Dist: matplotlib>=3.0.0; extra == "visualization"
Requires-Dist: open3d>=0.13.0; extra == "visualization"
Provides-Extra: dev
Requires-Dist: pytest>=6.0; extra == "dev"
Requires-Dist: pytest-cov; extra == "dev"
Requires-Dist: black; extra == "dev"
Requires-Dist: flake8; extra == "dev"
Requires-Dist: mypy; extra == "dev"
Requires-Dist: twine; extra == "dev"
Requires-Dist: build; extra == "dev"
Dynamic: license-file
